MANIFEST.in
README.md
setup.cfg
setup.py
collective/__init__.py
collective.geo.zugmap.egg-info/PKG-INFO
collective.geo.zugmap.egg-info/SOURCES.txt
collective.geo.zugmap.egg-info/dependency_links.txt
collective.geo.zugmap.egg-info/entry_points.txt
collective.geo.zugmap.egg-info/namespace_packages.txt
collective.geo.zugmap.egg-info/not-zip-safe
collective.geo.zugmap.egg-info/requires.txt
collective.geo.zugmap.egg-info/top_level.txt
collective/geo/__init__.py
collective/geo/zugmap/__init__.py
collective/geo/zugmap/configure.zcml
collective/geo/zugmap/maplayers.py
collective/geo/zugmap/maplayers.zcml
collective/geo/zugmap/sync.sh
collective/geo/zugmap/browser/__init__.py
collective/geo/zugmap/browser/configure.zcml
collective/geo/zugmap/browser/layers_templates/zugmap_orthofotoplus_layer.pt
collective/geo/zugmap/browser/layers_templates/zugmap_ortsplan_layer.pt
collective/geo/zugmap/profiles/default/metadata.xml
collective/geo/zugmap/tests/__init__.py
collective/geo/zugmap/tests/layer.py
docs/HISTORY.txt
docs/INSTALL.txt
docs/LICENSE.GPL
docs/LICENSE.txt