Metadata-Version: 1.1
Name: collective.geo.zugmap
Version: 1.0.6
Summary: Zugmap Layer for collective.geo
Home-page: https://github.com/collective/collective.geo.zugmap
Author: Seantis GmbH
Author-email: info@seantis.ch
License: GPL v2
Keywords: directory plone dexterity
Platform: UNKNOWN
Classifier: Framework :: Plone
Classifier: Framework :: Plone :: 4.3
Classifier: Framework :: Plone :: 5.1
Classifier: Programming Language :: Python
